{
  "stats": {
    "suites": 1,
    "tests": 1,
    "passes": 1,
    "pending": 0,
    "failures": 0,
    "start": "2021-02-03T16:29:02.597Z",
    "end": "2021-02-03T16:29:02.602Z",
    "duration": 5
  },
  "tests": [
    {
      "title": "must return the desired output",
      "fullTitle": "account.js must return the desired output",
      "duration": 1,
      "currentRetry": 0,
      "err": {}
    }
  ],
  "pending": [],
  "failures": [],
  "passes": [
    {
      "title": "must return the desired output",
      "fullTitle": "account.js must return the desired output",
      "duration": 1,
      "currentRetry": 0,
      "err": {}
    }
  ]
}